chronilog/__init__.py
chronilog/diagnostics.py
chronilog/cli/init.py
chronilog/cli/main.py
chronilog/core/config.py
chronilog/core/formatter.py
chronilog/core/handlers.py
chronilog/core/logger.py
chronilog/integrations/sentry.py
chronilog/utils/paths.py
chronilog-0.1.7.dist-info/licenses/LICENSE
chronilog-0.1.7.dist-info/METADATA
chronilog-0.1.7.dist-info/WHEEL
chronilog-0.1.7.dist-info/entry_points.txt
chronilog-0.1.7.dist-info/top_level.txt
chronilog-0.1.7.dist-info/RECORD
