Metadata-Version: 2.4
Name: chronilog
Version: 0.1.7
Summary: A clean, customizable logging package with rich formatting, diagnostics, and rotating file output.
Author-email: Brandon McKinney <brandonmckinney01@icloud.com>
License-Expression: MIT
Project-URL: Homepage, https://github.com/BrandonAustin01/Chronilog
Project-URL: Repository, https://github.com/BrandonAustin01/Chronilog
Project-URL: Issues, https://github.com/BrandonAustin01/Chronilog/issues
Keywords: logging,rich,diagnostics,file logging,cli,sentry
Classifier: Development Status :: 4 - Beta
Classifier: Intended Audience :: Developers
Classifier: Programming Language :: Python :: 3
Classifier: Programming Language :: Python :: 3.11
Classifier: Programming Language :: Python :: 3.12
Classifier: Operating System :: OS Independent
Classifier: Topic :: Software Development :: Libraries :: Python Modules
Classifier: Topic :: System :: Logging
Requires-Python: >=3.11
License-File: LICENSE
Requires-Dist: rich>=13.0.0
Requires-Dist: python-dotenv>=1.0.0
Dynamic: license-file
Dynamic: requires-python
